kjingbaoSDK/__init__.py
kjingbaoSDK/api/ClaimApiUtils.py
kjingbaoSDK/api/Encryption.py
kjingbaoSDK/api/PolicyApiUtils.py
kjingbaoSDK/api/__init__.py
kjingbaoSDK/constant/BaseAmountWay.py
kjingbaoSDK/constant/CargoCategory.py
kjingbaoSDK/constant/CargoCategoryTraditional.py
kjingbaoSDK/constant/CertificateType.py
kjingbaoSDK/constant/Currency.py
kjingbaoSDK/constant/Deliveryway.py
kjingbaoSDK/constant/DestType.py
kjingbaoSDK/constant/ExpressCompany.py
kjingbaoSDK/constant/Packing.py
kjingbaoSDK/constant/TransportMode.py
kjingbaoSDK/constant/__init__.py
kjingbaoSDK/ov/KJBConfig.py
kjingbaoSDK/ov/__init__.py
kjingbaoSDK/ov/claim/ClaimLinkParamDTO.py
kjingbaoSDK/ov/claim/ClaimShareDTO.py
kjingbaoSDK/ov/claim/__init__.py
kjingbaoSDK/ov/policy/InsuranceRiskApiDTO.py
kjingbaoSDK/ov/policy/PolicyApiDTO.py
kjingbaoSDK/ov/policy/PolicyApplicantApiDTO.py
kjingbaoSDK/ov/policy/PolicyAttachmentApiDTO.py
kjingbaoSDK/ov/policy/PolicyBatchApiDTO.py
kjingbaoSDK/ov/policy/PolicyInsuredApiDTO.py
kjingbaoSDK/ov/policy/PolicyLinkParamDTO.py
kjingbaoSDK/ov/policy/PolicyOwnerApiDTO.py
kjingbaoSDK/ov/policy/__init__.py
src/__init__.py
src/kjingbaoSDK/__init__.py
src/kjingbaoSDK/api/ClaimApiUtils.py
src/kjingbaoSDK/api/Encryption.py
src/kjingbaoSDK/api/PolicyApiUtils.py
src/kjingbaoSDK/api/__init__.py
src/kjingbaoSDK/constant/BaseAmountWay.py
src/kjingbaoSDK/constant/CargoCategory.py
src/kjingbaoSDK/constant/CargoCategoryTraditional.py
src/kjingbaoSDK/constant/CertificateType.py
src/kjingbaoSDK/constant/Currency.py
src/kjingbaoSDK/constant/Deliveryway.py
src/kjingbaoSDK/constant/DestType.py
src/kjingbaoSDK/constant/ExpressCompany.py
src/kjingbaoSDK/constant/Packing.py
src/kjingbaoSDK/constant/TransportMode.py
src/kjingbaoSDK/constant/__init__.py
src/kjingbaoSDK/ov/KJBConfig.py
src/kjingbaoSDK/ov/__init__.py
src/kjingbaoSDK/ov/claim/ClaimLinkParamDTO.py
src/kjingbaoSDK/ov/claim/ClaimShareDTO.py
src/kjingbaoSDK/ov/claim/__init__.py
src/kjingbaoSDK/ov/policy/InsuranceRiskApiDTO.py
kjb_open_sdk-1.0.4.dist-info/METADATA
kjb_open_sdk-1.0.4.dist-info/WHEEL
kjb_open_sdk-1.0.4.dist-info/top_level.txt
kjb_open_sdk-1.0.4.dist-info/RECORD
