Metadata-Version: 2.1
Name: kjb-open-sdk
Version: 1.0.4
Summary: kjb-open-sdk from kjingbao open platform
Author: Zhang yu
Author-email: zhangyu@kjingbao.com
Keywords: pip,kjb-open-sdk
Platform: any
Requires-Dist: pydantic >2.0
Requires-Dist: requests
